skekraft/HttpClient.py
skekraft/__init__.py
skekraft/api.py
skekraft/const.py
SkeKraft-0.0.3.dist-info/LICENSE.txt
SkeKraft-0.0.3.dist-info/METADATA
SkeKraft-0.0.3.dist-info/WHEEL
SkeKraft-0.0.3.dist-info/top_level.txt
SkeKraft-0.0.3.dist-info/RECORD
